.gitignore
MANIFEST.in
PKG-INFO
readme.md
run.sh
setup.py
.vscode/settings.json
docs/.gitignore
docs/LICENSE
docs/Makefile
docs/source/conf.py
docs/source/index.rst
docs/source/_extensions/jinja.py
docs/source/sciPyFoam/modules.rst
docs/source/sciPyFoam/sciPyFoam.postProcessing.rst
docs/source/sciPyFoam/sciPyFoam.rst
docs/source/sciPyFoam/postProcessing/modules.rst
docs/source/sciPyFoam/postProcessing/postProcessing.rst
docs/source/themes/rtd/Apache-License-2.0.txt
docs/source/themes/rtd/LICENSE
docs/source/themes/rtd/README.html
docs/source/themes/rtd/README.md
docs/source/themes/rtd/breadcrumbs.html
docs/source/themes/rtd/footer.html
docs/source/themes/rtd/layout.html
docs/source/themes/rtd/search.html
docs/source/themes/rtd/searchbox.html
docs/source/themes/rtd/theme.conf
docs/source/themes/rtd/versions.html
docs/source/themes/rtd/locale/sphinx.pot
docs/source/themes/rtd/locale/en/LC_MESSAGES/sphinx.mo
docs/source/themes/rtd/locale/en/LC_MESSAGES/sphinx.po
docs/source/themes/rtd/locale/es/LC_MESSAGES/sphinx.mo
docs/source/themes/rtd/locale/es/LC_MESSAGES/sphinx.po
docs/source/themes/rtd/locale/nl/LC_MESSAGES/sphinx.mo
docs/source/themes/rtd/locale/nl/LC_MESSAGES/sphinx.po
docs/source/themes/rtd/locale/ru/LC_MESSAGES/sphinx.mo
docs/source/themes/rtd/locale/ru/LC_MESSAGES/sphinx.po
docs/source/themes/rtd/static/css/badge_only.css
docs/source/themes/rtd/static/css/theme.css
docs/source/themes/rtd/static/fonts/FontAwesome.otf
docs/source/themes/rtd/static/fonts/Roboto-Slab-Bold.woff
docs/source/themes/rtd/static/fonts/Roboto-Slab-Bold.woff2
docs/source/themes/rtd/static/fonts/Roboto-Slab-Light.woff
docs/source/themes/rtd/static/fonts/Roboto-Slab-Light.woff2
docs/source/themes/rtd/static/fonts/Roboto-Slab-Regular.woff
docs/source/themes/rtd/static/fonts/Roboto-Slab-Regular.woff2
docs/source/themes/rtd/static/fonts/Roboto-Slab-Thin.woff
docs/source/themes/rtd/static/fonts/Roboto-Slab-Thin.woff2
docs/source/themes/rtd/static/fonts/fontawesome-webfont.eot
sciPyFoam.egg-info/PKG-INFO
sciPyFoam.egg-info/SOURCES.txt
sciPyFoam.egg-info/dependency_links.txt
sciPyFoam.egg-info/entry_points.txt
sciPyFoam.egg-info/requires.txt
sciPyFoam.egg-info/top_level.txt
