Metadata-Version: 1.0
Name: sciPyFoam
Version: 0.4.1
Summary: Visualize simulation results of OpenFOAM to publish qulity figure
Home-page: https://gitlab.com/hydrothermal-openfoam/scipyfoam
Author: Zhikui Guo
Author-email: zguo@geomar.de
License: UNKNOWN
Keywords: OpenFOAM publication figure SCI postprocessing
Platform: UNKNOWN
